statistical_tests/__init__.py
statistical_tests/tests.py
staty_tests-0.2.0.dist-info/LICENSE
staty_tests-0.2.0.dist-info/METADATA
staty_tests-0.2.0.dist-info/WHEEL
staty_tests-0.2.0.dist-info/top_level.txt
staty_tests-0.2.0.dist-info/RECORD
