Metadata-Version: 2.1
Name: staty-tests
Version: 0.2.0
Summary: A Python library for performing statistical tests like ANOVA and chi-square.
Home-page: https://github.com/solab5/statistical-tests
Author: Twinomugisha Morris
Author-email: morristwinomugisha2000@gmail.com
License: MIT
Classifier: Development Status :: 3 - Alpha
Classifier: Intended Audience :: Developers
Classifier: License :: OSI Approved :: MIT License
Classifier: Programming Language :: Python :: 3
Classifier: Programming Language :: Python :: 3.6
Classifier: Programming Language :: Python :: 3.7
Classifier: Programming Language :: Python :: 3.8
Classifier: Programming Language :: Python :: 3.9
License-File: LICENSE
Requires-Dist: scipy
Requires-Dist: pandas
Requires-Dist: tabulate
